AUTHORS.rst
CONTRIBUTING.rst
HISTORY.rst
LICENSE
MANIFEST.in
NOTICE.rst
README.rst
setup.py
forge/__init__.py
forge/cli.py
forge/forge.py
forge/module.py
forge/util.py
forge_cli.egg-info/PKG-INFO
forge_cli.egg-info/SOURCES.txt
forge_cli.egg-info/dependency_links.txt
forge_cli.egg-info/entry_points.txt
forge_cli.egg-info/not-zip-safe
forge_cli.egg-info/top_level.txt