Metadata-Version: 1.1
Name: forge-cli
Version: 0.2
Summary: forge is a command line tool that allows to execute modules to configure a linux system
Home-page: https://github.com/lacion/forge
Author: Luis Morales
Author-email: luismmorales@gmail.com
License: BSD
Keywords: forge
Platform: UNKNOWN
Classifier: Development Status :: 2 - Pre-Alpha
Classifier: Intended Audience :: Developers
Classifier: License :: OSI Approved :: BSD License
Classifier: Natural Language :: English
Classifier: Programming Language :: Python :: 2
Classifier: Programming Language :: Python :: 2.6
Classifier: Programming Language :: Python :: 2.7
